bankfind/__init__.py
bankfind/base.py
bankfind/main.py
bankfind/metadata/__init__.py
bankfind/metadata/failure.py
bankfind/metadata/history.py
bankfind/metadata/institution.py
bankfind/metadata/location.py
bankfind/metadata/summary.py
bankfind-0.0.1.dist-info/LICENSE
bankfind-0.0.1.dist-info/WHEEL
bankfind-0.0.1.dist-info/METADATA
bankfind-0.0.1.dist-info/RECORD
