Metadata-Version: 2.1
Name: bankfind
Version: 0.0.1
Summary: Python interface to the FDIC's API for publically available bank data
Home-page: https://github.com/dpguthrie/bankfind
License: UNKNOWN
Keywords: banking, finance, fdic, api, requests
Author: Doug Guthrie
Author-email: douglas.p.guthrie@gmail.com
Classifier: Development Status :: 3 - Alpha
Classifier: Intended Audience :: Developers
Classifier: Intended Audience :: Financial and Insurance Industry
Classifier: License :: OSI Approved :: MIT License
Classifier: Operating System :: OS Independent
Classifier: Programming Language :: Python
Classifier: Programming Language :: Python :: 2.7
Classifier: Programming Language :: Python :: 3.5
Classifier: Programming Language :: Python :: 3.6
Classifier: Programming Language :: Python :: 3.7
Classifier: Programming Language :: Python :: 3.8
Requires-Dist: requests == 2.24.0
Requires-Dist: pandas>=0.24
Requires-Dist: mkdocs-material ; extra == "doc"
Requires-Dist: pymdown-extensions ; extra == "doc"
Requires-Dist: pytest ; extra == "test"
Requires-Dist: coverage ; extra == "test"
Requires-Dist: pytest-cov ; extra == "test"
Project-URL: Documentation, https://bankfind.dpguthrie.com
Provides-Extra: doc
Provides-Extra: test
